aespark/__analysis.py
aespark/__broken.py
aespark/__chart.py
aespark/__dataclean.py
aespark/__document.py
aespark/__init__.py
aespark/__union.py
aespark/lcode/evolvement.py
aespark/static/bankBIN.txt
aespark/static/bankSimple.txt
aespark/static/cnarea_2020.txt
aespark/static/id_card_info.txt
aespark/static/ip_info.txt
aespark/static/jieba_word.txt
aespark/static/word.docx
aespark-1.6.dist-info/METADATA
aespark-1.6.dist-info/WHEEL
aespark-1.6.dist-info/top_level.txt
aespark-1.6.dist-info/RECORD
